riemannian_stats/__init__.py
riemannian_stats/data_processing.py
riemannian_stats/riemannian_analysis.py
riemannian_stats/utilities.py
riemannian_stats/visualization.py
riemannian_stats-0.1.1.dist-info/METADATA
riemannian_stats-0.1.1.dist-info/WHEEL
riemannian_stats-0.1.1.dist-info/licenses/LICENSE.txt
riemannian_stats-0.1.1.dist-info/RECORD
