Metadata-Version: 2.4
Name: riemannian_stats
Version: 0.1.1
Summary: Riemannian STATS is a package for applying Principal Component Analysis on Riemannian manifolds using UMAP-derived local geometry, enabling powerful dimensionality reduction and visualization for any type of data.
Project-URL: Homepage, https://riemannianstats.web.app
Project-URL: Repository, https://github.com/OldemarRodriguez/riemannian_stats.git
Author-email: Oldemar Rodríguez Rojas <oldemar.rodriguez@ucr.ac.cr>, Jennifer Lobo Vásquez <jennifer.lobo.vasquez@gmail.com>
License: BSD 3-Clause License
License-File: LICENSE.txt
Classifier: License :: OSI Approved :: BSD License
Classifier: Operating System :: OS Independent
Classifier: Programming Language :: Python :: 3
Requires-Python: >=3.8
Requires-Dist: matplotlib<3.11,>=3.7.5
Requires-Dist: numpy<3.0,>=1.24.4
Requires-Dist: pandas<2.3,>=2.0.3
Requires-Dist: scikit-learn<1.7,>=1.3.2
Requires-Dist: umap-learn<0.6,>=0.5.7
Provides-Extra: plot
Requires-Dist: matplotlib<3.11,>=3.7.5; extra == 'plot'
Requires-Dist: pandas<2.3,>=2.0.3; extra == 'plot'
